based/__init__.py
based/abcs.py
based/bitview.py
based/cli/__init__.py
based/cli/based/__init__.py
based/cli/based/__main__.py
based/converters/__init__.py
based/converters/bigint.py
based/converters/biterator.py
based/converters/slidingwindow.py
based/cpython_port.py
based/debug.py
based/exceptions.py
based/standards/__init__.py
based/standards/base32.py
based/standards/base46.py
based/standards/base62.py
based/standards/base64.py
based/standards/base85.py
based/standards/base94.py
pybased-0.0.2.dist-info/entry_points.txt
pybased-0.0.2.dist-info/LICENSE
pybased-0.0.2.dist-info/WHEEL
pybased-0.0.2.dist-info/METADATA
pybased-0.0.2.dist-info/RECORD
