Metadata-Version: 2.1
Name: pybased
Version: 0.0.2
Summary: Library for creating arbitrary binary encodings.  Includes variations on base32, base64, base85, and more.
Home-page: https://gitlab.com/N3X15/python-based
License: MIT
Author: Rob Nelson
Author-email: nexisentertainment@gmail.com
Requires-Python: >=3.8,<4.0
Classifier: License :: OSI Approved :: MIT License
Classifier: Programming Language :: Python :: 3
Classifier: Programming Language :: Python :: 3.10
Classifier: Programming Language :: Python :: 3.8
Classifier: Programming Language :: Python :: 3.9
Requires-Dist: click (>=8.1.3,<9.0.0)
Requires-Dist: frozendict (>=2.3.2,<3.0.0)
Requires-Dist: ruamel.yaml (>=0.17.21,<0.18.0)
Requires-Dist: tabulate (>=0.8.9,<0.9.0)
Project-URL: Repository, https://gitlab.com/N3X15/python-based
